numpy_unit/__init__.py
numpy_unit/examples.py
numpy_unit/tests.py
numpy_unit/unit.py
numpy_unit-0.1.1.dist-info/LICENSE
numpy_unit-0.1.1.dist-info/METADATA
numpy_unit-0.1.1.dist-info/WHEEL
numpy_unit-0.1.1.dist-info/top_level.txt
numpy_unit-0.1.1.dist-info/RECORD
