Metadata-Version: 2.1
Name: numpy-unit
Version: 0.1.1
Summary: A package providing an unit system for numpy multidimensionnal arrays.
Home-page: https://github.com/politinsa/numpy-unit
Author: Politinsa
License: UNKNOWN
Platform: UNKNOWN
Classifier: Programming Language :: Python :: 3
Classifier: Operating System :: OS Independent
Requires-Python: >=3.6
